{
  "schedule": [
    {
      "time_slot": "08:20-09:50",
      "week": [
        3,
        7,
        9,
        11,
        13,
        15
      ],
      "group": "PRLCOMP 1",
      "room": "1324 АУД.",
      "building": "Кронверкский пр., д.49, лит.А",
      "subject_name": "ПАРАЛЛЕЛЬНЫЕ ВЫЧИСЛЕНИЯ / PARALLEL COMPUTING (ЛАБ)",
      "lesson_format": "Очно - дистанционный"
    },
    {
      "time_slot": "10:00-11:30",
      "week": [
        3,
        7
      ],
      "group": "PRLCOMP 1",
      "room": "1324 АУД.",
      "building": "Кронверкский пр., д.49, лит.А",
      "subject_name": "ПАРАЛЛЕЛЬНЫЕ ВЫЧИСЛЕНИЯ / PARALLEL COMPUTING (ЛАБ)",
      "lesson_format": "Очно - дистанционный"
    },
    {
      "time_slot": "10:00-11:30",
      "week": [
        9,
        11,
        13
      ],
      "group": "PRLCOMP 1.1",
      "room": "1324 АУД.",
      "building": "Кронверкский пр., д.49, лит.А",
      "subject_name": "ПАРАЛЛЕЛЬНЫЕ ВЫЧИСЛЕНИЯ / PARALLEL COMPUTING (ЛАБ)",
      "lesson_format": "Очно - дистанционный"
    },
    {
      "time_slot": "10:00-11:30",
      "week": [
        2,
        4,
        6,
        8,
        12,
        14,
        16,
        18
      ],
      "group": "ИНФОРМ 3.4",
      "room": "2112 АУД.",
      "building": "Кронверкский пр., д.49, лит.А",
      "subject_name": "ИНФОРМАТИКА (ЛАБ)",
      "lesson_format": "Очно - дистанционный"
    },
    {
      "time_slot": "11:40-13:10",
      "week": [
        2,
        4,
        6,
        8,
        12,
        14,
        16,
        18
      ],
      "group": "ИНФОРМ 3.4",
      "room": "2112 АУД.",
      "building": "Кронверкский пр., д.49, лит.А",
      "subject_name": "ИНФОРМАТИКА (ЛАБ)",
      "lesson_format": "Очно - дистанционный"
    },
    {
      "time_slot": "13:30-15:00",
      "week": [
        3,
        7,
        9,
        11,
        13
      ],
      "group": "PRLCOMP 1.1",
      "room": "1324 АУД.",
      "building": "Кронверкский пр., д.49, лит.А",
      "subject_name": "ПАРАЛЛЕЛЬНЫЕ ВЫЧИСЛЕНИЯ / PARALLEL COMPUTING (ЛАБ)",
      "lesson_format": "Очно - дистанционный"
    },
    {
      "time_slot": "13:30-15:00",
      "week": [
        2,
        4,
        6,
        8,
        12,
        14,
        16,
        18
      ],
      "group": "ИНФОРМ 3.5",
      "room": "2112 АУД.",
      "building": "Кронверкский пр., д.49, лит.А",
      "subject_name": "ИНФОРМАТИКА (ЛАБ)",
      "lesson_format": "Очно - дистанционный"
    },
    {
      "time_slot": "15:20-16:50",
      "week": [
        2,
        4,
        6,
        8,
        12,
        14,
        16,
        18
      ],
      "group": "ИНФОРМ 3.5",
      "room": "2112 АУД.",
      "building": "Кронверкский пр., д.49, лит.А",
      "subject_name": "ИНФОРМАТИКА (ЛАБ)",
      "lesson_format": "Очно - дистанционный"
    }
  ]
}
